{
    "Ar36": {
        "error": 0.0002205326150181427,
        "error_type": "SEM",
        "filter_outliers_dict": {
            "filter_outliers": true,
            "iterations": 1,
            "std_devs": 2
        },
        "fit": "Parabolic",
        "fn": 321,
        "include_baseline_error": false,
        "n": 340,
        "reviewed": true,
        "value": 0.002332898006026857
    },
    "Ar37": {
        "error": 0.014929501779809902,
        "error_type": "SEM",
        "filter_outliers_dict": {
            "filter_outliers": true,
            "iterations": 1,
            "std_devs": 2
        },
        "fit": "Linear",
        "fn": 324,
        "include_baseline_error": false,
        "n": 340,
        "reviewed": true,
        "value": -0.11782214870593832
    },
    "Ar38": {
        "error": 0.006187699191257522,
        "error_type": "SEM",
        "filter_outliers_dict": {
            "filter_outliers": true,
            "iterations": 1,
            "std_devs": 2
        },
        "fit": "Linear",
        "fn": 322,
        "include_baseline_error": false,
        "n": 340,
        "reviewed": true,
        "value": 0.11310687168766023
    },
    "Ar39": {
        "error": 0.012782091983174601,
        "error_type": "SEM",
        "filter_outliers_dict": {
            "filter_outliers": true,
            "iterations": 1,
            "std_devs": 2
        },
        "fit": "Parabolic",
        "fn": 320,
        "include_baseline_error": false,
        "n": 340,
        "reviewed": true,
        "value": -0.0030089255320051504
    },
    "Ar40": {
        "error": 0.02638859987168302,
        "error_type": "SEM",
        "filter_outliers_dict": {
            "filter_outliers": true,
            "iterations": 1,
            "std_devs": 2
        },
        "fit": "Parabolic",
        "fn": 327,
        "include_baseline_error": false,
        "n": 340,
        "reviewed": true,
        "value": 0.4126970478052696
    }
}